application/__init__.py
application/cli.py
application/diagnose.py
application/install_hooks.py
application/match_test.py
application/suggest_rules.py
application/test_hook.py
domain/__init__.py
domain/entities/__init__.py
domain/hooks/__init__.py
domain/hooks/base_hook.py
domain/hooks/compact_detected_hook.py
domain/hooks/hook_response.py
domain/hooks/implementation_design_hook.py
domain/hooks/session_startup_hook.py
domain/hooks/subagent_event_hook.py
domain/hooks/suggest_rules_trigger.py
domain/services/__init__.py
domain/services/base_convention_matcher.py
domain/services/command_convention_matcher.py
domain/services/file_convention_matcher.py
domain/services/hook_manager.py
domain/services/rule_suggester.py
domain/services/subagent_marker_manager.py
infrastructure/__init__.py
infrastructure/config/__init__.py
infrastructure/config/config_manager.py
infrastructure/hooks/__init__.py
infrastructure/hooks/hook_executor.py
infrastructure/notifiers/__init__.py
infrastructure/notifiers/discord_notifier.py
shared/__init__.py
shared/constants.py
shared/permission_mode.py
shared/structured_logging.py
shared/version.py
shared/base/__init__.py
shared/base/base_cli.py
shared/utils/__init__.py
shared/utils/session_manager.py
claude_nagger-1.5.0.dist-info/METADATA
claude_nagger-1.5.0.dist-info/WHEEL
claude_nagger-1.5.0.dist-info/entry_points.txt
claude_nagger-1.5.0.dist-info/licenses/LICENSE
claude_nagger-1.5.0.dist-info/RECORD
