Metadata-Version: 2.4
Name: claude-nagger
Version: 1.5.0
Summary: Claude Code統合ツールシステム - フック・規約管理CLI
Project-URL: Homepage, https://github.com/HollySizzle/claude-nagger
Project-URL: Repository, https://github.com/HollySizzle/claude-nagger
Author: HollySizzle
License-Expression: MIT
License-File: LICENSE
Keywords: claude,claude-code,conventions,hooks
Classifier: Development Status :: 4 - Beta
Classifier: Environment :: Console
Classifier: Intended Audience :: Developers
Classifier: License :: OSI Approved :: MIT License
Classifier: Programming Language :: Python :: 3
Classifier: Programming Language :: Python :: 3.10
Classifier: Programming Language :: Python :: 3.11
Classifier: Programming Language :: Python :: 3.12
Classifier: Programming Language :: Python :: 3.13
Requires-Python: >=3.10
Requires-Dist: aiohttp>=3.8.0
Requires-Dist: json5>=0.9.14
Requires-Dist: pytz>=2023.3
Requires-Dist: pyyaml>=6.0
Requires-Dist: questionary>=2.0.0
Requires-Dist: rich>=13.0.0
Requires-Dist: typing-extensions>=4.8.0
Requires-Dist: wcmatch>=10.0
Provides-Extra: dev
Requires-Dist: pytest-asyncio>=0.21.0; extra == 'dev'
Requires-Dist: pytest-cov>=4.0.0; extra == 'dev'
Requires-Dist: pytest>=7.0.0; extra == 'dev'
